MANIFEST.in
README.rst
setup.cfg
setup.py
accessstats/__init__.py
accessstats/client.py
accessstats/queries.py
accessstats/thrift/access_stats.thrift
accessstatsapi.egg-info/PKG-INFO
accessstatsapi.egg-info/SOURCES.txt
accessstatsapi.egg-info/dependency_links.txt
accessstatsapi.egg-info/requires.txt
accessstatsapi.egg-info/top_level.txt