Metadata-Version: 1.1
Name: accessstatsapi
Version: 1.2.1
Summary: SciELO AccessStats service SDK for Python
Home-page: http://github.com/scieloorg/accessstatsapi
Author: SciELO
Author-email: scielo-dev@googlegroups.com
License: UNKNOWN
Platform: UNKNOWN
Classifier: Development Status :: 4 - Beta
Classifier: Intended Audience :: Developers
Classifier: Programming Language :: Python :: 3
